setup.py
shinkenplugins/__init__.py
shinkenplugins.plugins.drupal_jenkins.egg-info/PKG-INFO
shinkenplugins.plugins.drupal_jenkins.egg-info/SOURCES.txt
shinkenplugins.plugins.drupal_jenkins.egg-info/dependency_links.txt
shinkenplugins.plugins.drupal_jenkins.egg-info/entry_points.txt
shinkenplugins.plugins.drupal_jenkins.egg-info/namespace_packages.txt
shinkenplugins.plugins.drupal_jenkins.egg-info/requires.txt
shinkenplugins.plugins.drupal_jenkins.egg-info/top_level.txt
shinkenplugins/plugins/__init__.py
shinkenplugins/plugins/drupal_jenkins/__init__.py
shinkenplugins/plugins/drupal_jenkins/drupal_jenkins.py